[
  { "id": "v-1", "infinitive": "לכתוב", "infinitiveTranslit": "likhtov", "root": "כ-ת-ב", "english": "to write", "tense": "past", "person": "אני", "conjugated": "כתבתי", "conjugatedTranslit": "katavti" },
  { "id": "v-2", "infinitive": "לכתוב", "infinitiveTranslit": "likhtov", "root": "כ-ת-ב", "english": "to write", "tense": "past", "person": "אתה", "conjugated": "כתבת", "conjugatedTranslit": "katavta" },
  { "id": "v-3", "infinitive": "לכתוב", "infinitiveTranslit": "likhtov", "root": "כ-ת-ב", "english": "to write", "tense": "present", "person": "אני/הוא", "conjugated": "כותב", "conjugatedTranslit": "kotev" },
  { "id": "v-4", "infinitive": "לכתוב", "infinitiveTranslit": "likhtov", "root": "כ-ת-ב", "english": "to write", "tense": "future", "person": "אני", "conjugated": "אכתוב", "conjugatedTranslit": "ekhtov" },
  { "id": "v-5", "infinitive": "לאכול", "infinitiveTranslit": "le'ekhol", "root": "א-כ-ל", "english": "to eat", "tense": "past", "person": "אני", "conjugated": "אכלתי", "conjugatedTranslit": "akhalti" },
  { "id": "v-6", "infinitive": "לאכול", "infinitiveTranslit": "le'ekhol", "root": "א-כ-ל", "english": "to eat", "tense": "present", "person": "אני/הוא", "conjugated": "אוכל", "conjugatedTranslit": "okhel" },
  { "id": "v-7", "infinitive": "לאכול", "infinitiveTranslit": "le'ekhol", "root": "א-כ-ל", "english": "to eat", "tense": "future", "person": "אני", "conjugated": "אוכל", "conjugatedTranslit": "okhal" },
  { "id": "v-8", "infinitive": "לשתות", "infinitiveTranslit": "lishtot", "root": "ש-ת-ה", "english": "to drink", "tense": "past", "person": "אני", "conjugated": "שתיתי", "conjugatedTranslit": "shatiti" },
  { "id": "v-9", "infinitive": "לשתות", "infinitiveTranslit": "lishtot", "root": "ש-ת-ה", "english": "to drink", "tense": "present", "person": "אני/הוא", "conjugated": "שותה", "conjugatedTranslit": "shote" },
  { "id": "v-10", "infinitive": "לשתות", "infinitiveTranslit": "lishtot", "root": "ש-ת-ה", "english": "to drink", "tense": "future", "person": "אני", "conjugated": "אשתה", "conjugatedTranslit": "eshte" },
  { "id": "v-11", "infinitive": "ללכת", "infinitiveTranslit": "lalekhet", "root": "ה-ל-כ", "english": "to go/walk", "tense": "past", "person": "אני", "conjugated": "הלכתי", "conjugatedTranslit": "halakhti" },
  { "id": "v-12", "infinitive": "ללכת", "infinitiveTranslit": "lalekhet", "root": "ה-ל-כ", "english": "to go/walk", "tense": "present", "person": "אני/הוא", "conjugated": "הולך", "conjugatedTranslit": "holekh" },
  { "id": "v-13", "infinitive": "ללכת", "infinitiveTranslit": "lalekhet", "root": "ה-ל-כ", "english": "to go/walk", "tense": "future", "person": "אני", "conjugated": "אלך", "conjugatedTranslit": "elekh" },
  { "id": "v-14", "infinitive": "לראות", "infinitiveTranslit": "lir'ot", "root": "ר-א-ה", "english": "to see", "tense": "past", "person": "אני", "conjugated": "ראיתי", "conjugatedTranslit": "ra'iti" },
  { "id": "v-15", "infinitive": "לראות", "infinitiveTranslit": "lir'ot", "root": "ר-א-ה", "english": "to see", "tense": "present", "person": "אני/הוא", "conjugated": "רואה", "conjugatedTranslit": "ro'e" },
  { "id": "v-16", "infinitive": "לראות", "infinitiveTranslit": "lir'ot", "root": "ר-א-ה", "english": "to see", "tense": "future", "person": "אני", "conjugated": "אראה", "conjugatedTranslit": "er'e" },
  { "id": "v-17", "infinitive": "לשמוע", "infinitiveTranslit": "lishmoa", "root": "ש-מ-ע", "english": "to hear", "tense": "past", "person": "אני", "conjugated": "שמעתי", "conjugatedTranslit": "shamati" },
  { "id": "v-18", "infinitive": "לשמוע", "infinitiveTranslit": "lishmoa", "root": "ש-מ-ע", "english": "to hear", "tense": "present", "person": "אני/הוא", "conjugated": "שומע", "conjugatedTranslit": "shomea" },
  { "id": "v-19", "infinitive": "לשמוע", "infinitiveTranslit": "lishmoa", "root": "ש-מ-ע", "english": "to hear", "tense": "future", "person": "אני", "conjugated": "אשמע", "conjugatedTranslit": "eshma" },
  { "id": "v-20", "infinitive": "לדבר", "infinitiveTranslit": "ledaber", "root": "ד-ב-ר", "english": "to speak", "tense": "past", "person": "אני", "conjugated": "דיברתי", "conjugatedTranslit": "dibarti" },
  { "id": "v-21", "infinitive": "לדבר", "infinitiveTranslit": "ledaber", "root": "ד-ב-ר", "english": "to speak", "tense": "present", "person": "אני/הוא", "conjugated": "מדבר", "conjugatedTranslit": "medaber" },
  { "id": "v-22", "infinitive": "לדבר", "infinitiveTranslit": "ledaber", "root": "ד-ב-ר", "english": "to speak", "tense": "future", "person": "אני", "conjugated": "אדבר", "conjugatedTranslit": "adaber" },
  { "id": "v-23", "infinitive": "לעבוד", "infinitiveTranslit": "la'avod", "root": "ע-ב-ד", "english": "to work", "tense": "past", "person": "אני", "conjugated": "עבדתי", "conjugatedTranslit": "avadeti" },
  { "id": "v-24", "infinitive": "לעבוד", "infinitiveTranslit": "la'avod", "root": "ע-ב-ד", "english": "to work", "tense": "present", "person": "אני/הוא", "conjugated": "עובד", "conjugatedTranslit": "oved" },
  { "id": "v-25", "infinitive": "לעבוד", "infinitiveTranslit": "la'avod", "root": "ע-ב-ד", "english": "to work", "tense": "future", "person": "אני", "conjugated": "אעבוד", "conjugatedTranslit": "e'evod" },
  { "id": "v-26", "infinitive": "ללמוד", "infinitiveTranslit": "lilmod", "root": "ל-מ-ד", "english": "to learn", "tense": "past", "person": "אני", "conjugated": "למדתי", "conjugatedTranslit": "lamadeti" },
  { "id": "v-27", "infinitive": "ללמוד", "infinitiveTranslit": "lilmod", "root": "ל-מ-ד", "english": "to learn", "tense": "present", "person": "אני/הוא", "conjugated": "לומד", "conjugatedTranslit": "lomed" },
  { "id": "v-28", "infinitive": "ללמוד", "infinitiveTranslit": "lilmod", "root": "ל-מ-ד", "english": "to learn", "tense": "future", "person": "אני", "conjugated": "אלמד", "conjugatedTranslit": "elmad" },
  { "id": "v-29", "infinitive": "לרצות", "infinitiveTranslit": "lirtsot", "root": "ר-צ-ה", "english": "to want", "tense": "past", "person": "אני", "conjugated": "רציתי", "conjugatedTranslit": "ratsiti" },
  { "id": "v-30", "infinitive": "לרצות", "infinitiveTranslit": "lirtsot", "root": "ר-צ-ה", "english": "to want", "tense": "present", "person": "אני/הוא", "conjugated": "רוצה", "conjugatedTranslit": "rotse" }
]
